hvf_extraction_script/__init__.py
hvf_extraction_script/hvf_data/__init__.py
hvf_extraction_script/hvf_data/hvf_object.py
hvf_extraction_script/hvf_data/hvf_perc_icon.py
hvf_extraction_script/hvf_data/hvf_plot_array.py
hvf_extraction_script/hvf_data/hvf_value.py
hvf_extraction_script/hvf_data/other_icons/__init__.py
hvf_extraction_script/hvf_data/other_icons/icon_triangle_v1.PNG
hvf_extraction_script/hvf_data/other_icons/icon_triangle_v2.PNG
hvf_extraction_script/hvf_data/perc_icons/__init__.py
hvf_extraction_script/hvf_data/perc_icons/perc_1.JPG
hvf_extraction_script/hvf_data/perc_icons/perc_2.JPG
hvf_extraction_script/hvf_data/perc_icons/perc_5.JPG
hvf_extraction_script/hvf_data/perc_icons/perc_half.JPG
hvf_extraction_script/hvf_data/perc_icons/perc_normal.JPG
hvf_extraction_script/hvf_data/value_icons/__init__.py
hvf_extraction_script/hvf_data/value_icons/v0/__init__.py
hvf_extraction_script/hvf_data/value_icons/v0/value_0.PNG
hvf_extraction_script/hvf_data/value_icons/v0/value_1.PNG
hvf_extraction_script/hvf_data/value_icons/v0/value_2.PNG
hvf_extraction_script/hvf_data/value_icons/v0/value_3.PNG
hvf_extraction_script/hvf_data/value_icons/v0/value_4.PNG
hvf_extraction_script/hvf_data/value_icons/v0/value_5.PNG
hvf_extraction_script/hvf_data/value_icons/v0/value_6.PNG
hvf_extraction_script/hvf_data/value_icons/v0/value_7.PNG
hvf_extraction_script/hvf_data/value_icons/v0/value_8.PNG
hvf_extraction_script/hvf_data/value_icons/v0/value_9.PNG
hvf_extraction_script/hvf_data/value_icons/v0/value_less_than.PNG
hvf_extraction_script/hvf_data/value_icons/v0/value_minus.PNG
hvf_extraction_script/hvf_data/value_icons/v1/__init__.py
hvf_extraction_script/hvf_data/value_icons/v1/value_0.PNG
hvf_extraction_script/hvf_data/value_icons/v1/value_1.PNG
hvf_extraction_script/hvf_data/value_icons/v1/value_2.PNG
hvf_extraction_script/hvf_data/value_icons/v1/value_3.PNG
hvf_extraction_script/hvf_data/value_icons/v1/value_4.PNG
hvf_extraction_script/hvf_data/value_icons/v1/value_5.PNG
hvf_extraction_script-0.0.4.dist-info/LICENSE.txt
hvf_extraction_script-0.0.4.dist-info/METADATA
hvf_extraction_script-0.0.4.dist-info/WHEEL
hvf_extraction_script-0.0.4.dist-info/top_level.txt
hvf_extraction_script-0.0.4.dist-info/RECORD
